TT_auth_system/__init__.py
TT_auth_system/auth.py
TT_auth_system-2.3.12.dist-info/LICENSE
TT_auth_system-2.3.12.dist-info/METADATA
TT_auth_system-2.3.12.dist-info/WHEEL
TT_auth_system-2.3.12.dist-info/top_level.txt
TT_auth_system-2.3.12.dist-info/RECORD
