Metadata-Version: 2.1
Name: TT-auth-system
Version: 2.3.12
Summary: An authentication system with one-time login links, templated email sending, and SQLite database support
Home-page: https://github.com/jarod-johnson-23/TT24_otc_generator
Author: Jarod Johnson
Author-email: jarodjohnson1001@gmail.com
Classifier: Programming Language :: Python :: 3
Classifier: License :: OSI Approved :: MIT License
Classifier: Operating System :: OS Independent
Requires-Python: >=3.6
License-File: LICENSE
Requires-Dist: python-dotenv
Requires-Dist: jinja2
Requires-Dist: cryptography
Requires-Dist: sqlalchemy
